sophon/__init__.py
sophon/sail.py
sophon/version.py
sophon-0.0.1.dist-info/LICENSE
sophon-0.0.1.dist-info/METADATA
sophon-0.0.1.dist-info/WHEEL
sophon-0.0.1.dist-info/top_level.txt
sophon-0.0.1.dist-info/RECORD
