Metadata-Version: 2.1
Name: sophon
Version: 0.0.1
Summary: Sophon Artificial Intelligent Library for deep learning on Sophon products.
Home-page: https://github.com/sophon-ai-algo/sophon-inference
Author: Sophon algorithm team
Author-email: developer@sophgo.com
Project-URL: Bug Tracker, https://github.com/sophon-ai-algo/sophon-inference/issues
Classifier: Development Status :: 3 - Alpha
Classifier: Intended Audience :: Developers
Classifier: Topic :: Software Development :: Libraries
Classifier: Programming Language :: Python :: 3
Classifier: License :: OSI Approved :: Apache Software License
Classifier: Operating System :: OS Independent
Requires-Python: >=3.5
License-File: LICENSE
